json_validator/__init__.py
json_validator/validator.py
sonic182_json_validator-1.0.2.dist-info/METADATA
sonic182_json_validator-1.0.2.dist-info/RECORD
sonic182_json_validator-1.0.2.dist-info/WHEEL
sonic182_json_validator-1.0.2.dist-info/top_level.txt
