Metadata-Version: 2.1
Name: sonic182-json-validator
Version: 1.0.2
Summary: A custom json validator
Home-page: https://github.com/sonic182/json_validator
Author: Johanderson Mogollon
Author-email: johanderson@mogollon.com.ve
License: MIT
Keywords: json validator dictionary
Platform: UNKNOWN
Classifier: Development Status :: 5 - Production/Stable
Classifier: Intended Audience :: Developers
Classifier: Topic :: Software Development
Classifier: License :: OSI Approved :: MIT License
Classifier: Programming Language :: Python :: 2
Classifier: Programming Language :: Python :: 2.7
Classifier: Programming Language :: Python :: 3.3
Classifier: Programming Language :: Python :: 3.4
Classifier: Programming Language :: Python :: 3.5
Classifier: Programming Language :: Python :: 3.6
Provides-Extra: test
Provides-Extra: dev
Provides-Extra: dev
Requires-Dist: astroid (==1.6.0); extra == 'dev'
Requires-Dist: autopep8 (==1.3.3); extra == 'dev'
Requires-Dist: docstrings (==1.3.0); extra == 'dev'
Requires-Dist: polyfill (==1.0.2); extra == 'dev'
Requires-Dist: flake8 (==3.5.0); extra == 'dev'
Requires-Dist: isort (==4.2.15); extra == 'dev'
Requires-Dist: proxy (==1.3.1); extra == 'dev'
Requires-Dist: mccabe (==0.6.1); extra == 'dev'
Requires-Dist: pycodestyle (==2.3.1); extra == 'dev'
Requires-Dist: pydocstyle (==2.1.1); extra == 'dev'
Requires-Dist: pyflakes (==1.6.0); extra == 'dev'
Requires-Dist: pylint (==1.8.1); extra == 'dev'
Requires-Dist: six (==1.11.0); extra == 'dev'
Requires-Dist: snowballstemmer (==1.2.1); extra == 'dev'
Requires-Dist: wrapt (==1.10.11); extra == 'dev'
Provides-Extra: test
Requires-Dist: attrs (==17.4.0); extra == 'test'
Requires-Dist: coverage (==4.4.2); extra == 'test'
Requires-Dist: gprof2dot (==2017.9.19); extra == 'test'
Requires-Dist: mock (==2.0.0); extra == 'test'
Requires-Dist: pbr (==3.1.1); extra == 'test'
Requires-Dist: pluggy (==0.6.0); extra == 'test'
Requires-Dist: py (==1.5.2); extra == 'test'
Requires-Dist: cov (==2.5.1); extra == 'test'
Requires-Dist: mock (==1.6.3); extra == 'test'
Requires-Dist: profiling (==1.2.11); extra == 'test'
Requires-Dist: pytest (==3.3.2); extra == 'test'
Requires-Dist: six (==1.11.0); extra == 'test'
